gymmick/__init__.py
gymmick/creategym.py
gymmick/members.py
gymmick-1.0.0.dist-info/LICENSE.txt
gymmick-1.0.0.dist-info/METADATA
gymmick-1.0.0.dist-info/WHEEL
gymmick-1.0.0.dist-info/top_level.txt
gymmick-1.0.0.dist-info/RECORD
