Metadata-Version: 2.1
Name: gymmick
Version: 1.0.0
Summary: Simple functionality for the creation of visuals-based OpenAI Gym environments.
Home-page: https://github.com/GithubDev939/gymmick
Download-URL: https://pypi.org/project/gymmick/
Author: Abhay Raj
Author-email: abhraj.work@gmail.com
License: MIT
Keywords: Gym,OpenAI,Environment,ReinforcementLearning
License-File: LICENSE.txt
Requires-Dist: pygame
Requires-Dist: numpy
Requires-Dist: gym
